CHANGES.txt
Kookbook.py
MANIFEST.in
MIT-LICENSE
Properties.py
README.txt
setup.py
bin/kk
bin/pykook
doc/docstyle.css
doc/fig001.png
doc/users-guide.html
examples/Kookbook_deploy.py
lib/Kook.egg-info/PKG-INFO
lib/Kook.egg-info/SOURCES.txt
lib/Kook.egg-info/dependency_links.txt
lib/Kook.egg-info/top_level.txt
lib/kook/__init__.py
lib/kook/commands.py
lib/kook/config.py
lib/kook/cookbook.py
lib/kook/decorators.py
lib/kook/kitchen.py
lib/kook/main.py
lib/kook/misc.py
lib/kook/remote.py
lib/kook/utils.py
lib/kook/books/all.py
lib/kook/books/clean.py
lib/kook/books/concatenate.py
test/_testhelper.py
test/books_test.py
test/commands_test.py
test/cookbook_test.py
test/decorators_test.py
test/kitchen_test.py
test/main_test.py
test/misc_test.py
test/remote_test.py
test/utils_test.py